mcp_email_agent/__init__.py
mcp_email_agent/config.py
mcp_email_agent/gmail.py
mcp_email_agent/main.py
mcp_email_agent/processor.py
mcp_email_agent-0.1.1.dist-info/METADATA
mcp_email_agent-0.1.1.dist-info/WHEEL
mcp_email_agent-0.1.1.dist-info/entry_points.txt
mcp_email_agent-0.1.1.dist-info/RECORD
